XDMFWrite_h5py/__init__.py
XDMFWrite_h5py/_version.py
XDMFWrite_h5py-0.2.0.dist-info/LICENSE
XDMFWrite_h5py-0.2.0.dist-info/METADATA
XDMFWrite_h5py-0.2.0.dist-info/WHEEL
XDMFWrite_h5py-0.2.0.dist-info/top_level.txt
XDMFWrite_h5py-0.2.0.dist-info/RECORD
